pyprivpackage/__init__.py
pyprivpackage/module1.py
pyprivpackage-0.1.0.dist-info/LICENSE
pyprivpackage-0.1.0.dist-info/METADATA
pyprivpackage-0.1.0.dist-info/WHEEL
pyprivpackage-0.1.0.dist-info/top_level.txt
pyprivpackage-0.1.0.dist-info/RECORD
