Metadata-Version: 2.1
Name: pyprivpackage
Version: 0.1.0
Summary: Dependency Confusion Test
Home-page: https://github.com/tomchen/example_pypi_package
Author: intrapus
Author-email: dev@intrapus.com
Project-URL: Documentation, https://github.com/intrapus/jango
Project-URL: Bug Reports, https://github.com/intrapus/jango/issues
Project-URL: Source Code, https://github.com/intrapus/jango
Keywords: example,pypi,package
Classifier: Development Status :: 5 - Production/Stable
Classifier: Intended Audience :: Developers
Classifier: Topic :: Software Development :: Build Tools
Classifier: Programming Language :: Python :: 3
Classifier: Programming Language :: Python :: 3.6
Classifier: Programming Language :: Python :: 3.7
Classifier: Programming Language :: Python :: 3.8
Classifier: Programming Language :: Python :: 3.9
Classifier: Programming Language :: Python :: 3 :: Only
Classifier: License :: OSI Approved :: MIT License
Classifier: Operating System :: OS Independent
Requires-Python: >=3.6
License-File: LICENSE
Provides-Extra: dev
Requires-Dist: check-manifest ; extra == 'dev'
